{
  "sentences": [
    {
      "index": 0,
      "parse": "(ROOT\n  (S\n    (S\n      (NP (PRP$ My) (NN father))\n      (VP (VBD wished)\n        (NP (PRP us))\n        (, ,)\n        (PP (IN as)\n          (NP (NNS schoolboys)))\n        (, ,)\n        (S\n          (VP (TO to)\n            (VP (VB speak)\n              (ADVP (RB well)))))))\n    (, ,)\n    (CC but)\n    (S\n      (NP (PRP he))\n      (VP (MD would)\n        (ADVP (RB never))\n        (VP (VB wish)\n          (NP (PRP$ his) (JJ grownup) (NNS daughters))\n          (S\n            (VP (TO to)\n              (VP (VB be)\n                (VP (VBG acting)\n                  (NP (NNS plays)))))))))\n    (. .)))",
      "basic-dependencies": [
        {
          "dep": "ROOT",
          "governor": 0,
          "governorGloss": "ROOT",
          "dependent": 3,
          "dependentGloss": "wished"
        },
        {
          "dep": "nmod:poss",
          "governor": 2,
          "governorGloss": "father",
          "dependent": 1,
          "dependentGloss": "My"
        },
        {
          "dep": "nsubj",
          "governor": 3,
          "governorGloss": "wished",
          "dependent": 2,
          "dependentGloss": "father"
        },
        {
          "dep": "dobj",
          "governor": 3,
          "governorGloss": "wished",
          "dependent": 4,
          "dependentGloss": "us"
        },
        {
          "dep": "punct",
          "governor": 3,
          "governorGloss": "wished",
          "dependent": 5,
          "dependentGloss": ","
        },
        {
          "dep": "case",
          "governor": 7,
          "governorGloss": "schoolboys",
          "dependent": 6,
          "dependentGloss": "as"
        },
        {
          "dep": "nmod",
          "governor": 3,
          "governorGloss": "wished",
          "dependent": 7,
          "dependentGloss": "schoolboys"
        },
        {
          "dep": "punct",
          "governor": 3,
          "governorGloss": "wished",
          "dependent": 8,
          "dependentGloss": ","
        },
        {
          "dep": "mark",
          "governor": 10,
          "governorGloss": "speak",
          "dependent": 9,
          "dependentGloss": "to"
        },
        {
          "dep": "xcomp",
          "governor": 3,
          "governorGloss": "wished",
          "dependent": 10,
          "dependentGloss": "speak"
        },
        {
          "dep": "advmod",
          "governor": 10,
          "governorGloss": "speak",
          "dependent": 11,
          "dependentGloss": "well"
        },
        {
          "dep": "punct",
          "governor": 3,
          "governorGloss": "wished",
          "dependent": 12,
          "dependentGloss": ","
        },
        {
          "dep": "cc",
          "governor": 3,
          "governorGloss": "wished",
          "dependent": 13,
          "dependentGloss": "but"
        },
        {
          "dep": "nsubj",
          "governor": 17,
          "governorGloss": "wish",
          "dependent": 14,
          "dependentGloss": "he"
        },
        {
          "dep": "aux",
          "governor": 17,
          "governorGloss": "wish",
          "dependent": 15,
          "dependentGloss": "would"
        },
        {
          "dep": "neg",
          "governor": 17,
          "governorGloss": "wish",
          "dependent": 16,
          "dependentGloss": "never"
        },
        {
          "dep": "conj",
          "governor": 3,
          "governorGloss": "wished",
          "dependent": 17,
          "dependentGloss": "wish"
        },
        {
          "dep": "nmod:poss",
          "governor": 20,
          "governorGloss": "daughters",
          "dependent": 18,
          "dependentGloss": "his"
        },
        {
          "dep": "amod",
          "governor": 20,
          "governorGloss": "daughters",
          "dependent": 19,
          "dependentGloss": "grownup"
        },
        {
          "dep": "dobj",
          "governor": 17,
          "governorGloss": "wish",
          "dependent": 20,
          "dependentGloss": "daughters"
        },
        {
          "dep": "mark",
          "governor": 23,
          "governorGloss": "acting",
          "dependent": 21,
          "dependentGloss": "to"
        },
        {
          "dep": "aux",
          "governor": 23,
          "governorGloss": "acting",
          "dependent": 22,
          "dependentGloss": "be"
        },
        {
          "dep": "xcomp",
          "governor": 17,
          "governorGloss": "wish",
          "dependent": 23,
          "dependentGloss": "acting"
        },
        {
          "dep": "dobj",
          "governor": 23,
          "governorGloss": "acting",
          "dependent": 24,
          "dependentGloss": "plays"
        },
        {
          "dep": "punct",
          "governor": 3,
          "governorGloss": "wished",
          "dependent": 25,
          "dependentGloss": "."
        }
      ],
      "collapsed-dependencies": [
        {
          "dep": "ROOT",
          "governor": 0,
          "governorGloss": "ROOT",
          "dependent": 3,
          "dependentGloss": "wished"
        },
        {
          "dep": "nmod:poss",
          "governor": 2,
          "governorGloss": "father",
          "dependent": 1,
          "dependentGloss": "My"
        },
        {
          "dep": "nsubj",
          "governor": 3,
          "governorGloss": "wished",
          "dependent": 2,
          "dependentGloss": "father"
        },
        {
          "dep": "dobj",
          "governor": 3,
          "governorGloss": "wished",
          "dependent": 4,
          "dependentGloss": "us"
        },
        {
          "dep": "punct",
          "governor": 3,
          "governorGloss": "wished",
          "dependent": 5,
          "dependentGloss": ","
        },
        {
          "dep": "case",
          "governor": 7,
          "governorGloss": "schoolboys",
          "dependent": 6,
          "dependentGloss": "as"
        },
        {
          "dep": "nmod:as",
          "governor": 3,
          "governorGloss": "wished",
          "dependent": 7,
          "dependentGloss": "schoolboys"
        },
        {
          "dep": "punct",
          "governor": 3,
          "governorGloss": "wished",
          "dependent": 8,
          "dependentGloss": ","
        },
        {
          "dep": "mark",
          "governor": 10,
          "governorGloss": "speak",
          "dependent": 9,
          "dependentGloss": "to"
        },
        {
          "dep": "xcomp",
          "governor": 3,
          "governorGloss": "wished",
          "dependent": 10,
          "dependentGloss": "speak"
        },
        {
          "dep": "advmod",
          "governor": 10,
          "governorGloss": "speak",
          "dependent": 11,
          "dependentGloss": "well"
        },
        {
          "dep": "punct",
          "governor": 3,
          "governorGloss": "wished",
          "dependent": 12,
          "dependentGloss": ","
        },
        {
          "dep": "cc",
          "governor": 3,
          "governorGloss": "wished",
          "dependent": 13,
          "dependentGloss": "but"
        },
        {
          "dep": "nsubj",
          "governor": 17,
          "governorGloss": "wish",
          "dependent": 14,
          "dependentGloss": "he"
        },
        {
          "dep": "aux",
          "governor": 17,
          "governorGloss": "wish",
          "dependent": 15,
          "dependentGloss": "would"
        },
        {
          "dep": "neg",
          "governor": 17,
          "governorGloss": "wish",
          "dependent": 16,
          "dependentGloss": "never"
        },
        {
          "dep": "conj:but",
          "governor": 3,
          "governorGloss": "wished",
          "dependent": 17,
          "dependentGloss": "wish"
        },
        {
          "dep": "nmod:poss",
          "governor": 20,
          "governorGloss": "daughters",
          "dependent": 18,
          "dependentGloss": "his"
        },
        {
          "dep": "amod",
          "governor": 20,
          "governorGloss": "daughters",
          "dependent": 19,
          "dependentGloss": "grownup"
        },
        {
          "dep": "dobj",
          "governor": 17,
          "governorGloss": "wish",
          "dependent": 20,
          "dependentGloss": "daughters"
        },
        {
          "dep": "mark",
          "governor": 23,
          "governorGloss": "acting",
          "dependent": 21,
          "dependentGloss": "to"
        },
        {
          "dep": "aux",
          "governor": 23,
          "governorGloss": "acting",
          "dependent": 22,
          "dependentGloss": "be"
        },
        {
          "dep": "xcomp",
          "governor": 17,
          "governorGloss": "wish",
          "dependent": 23,
          "dependentGloss": "acting"
        },
        {
          "dep": "dobj",
          "governor": 23,
          "governorGloss": "acting",
          "dependent": 24,
          "dependentGloss": "plays"
        },
        {
          "dep": "punct",
          "governor": 3,
          "governorGloss": "wished",
          "dependent": 25,
          "dependentGloss": "."
        }
      ],
      "collapsed-ccprocessed-dependencies": [
        {
          "dep": "ROOT",
          "governor": 0,
          "governorGloss": "ROOT",
          "dependent": 3,
          "dependentGloss": "wished"
        },
        {
          "dep": "nmod:poss",
          "governor": 2,
          "governorGloss": "father",
          "dependent": 1,
          "dependentGloss": "My"
        },
        {
          "dep": "nsubj",
          "governor": 3,
          "governorGloss": "wished",
          "dependent": 2,
          "dependentGloss": "father"
        },
        {
          "dep": "dobj",
          "governor": 3,
          "governorGloss": "wished",
          "dependent": 4,
          "dependentGloss": "us"
        },
        {
          "dep": "punct",
          "governor": 3,
          "governorGloss": "wished",
          "dependent": 5,
          "dependentGloss": ","
        },
        {
          "dep": "case",
          "governor": 7,
          "governorGloss": "schoolboys",
          "dependent": 6,
          "dependentGloss": "as"
        },
        {
          "dep": "nmod:as",
          "governor": 3,
          "governorGloss": "wished",
          "dependent": 7,
          "dependentGloss": "schoolboys"
        },
        {
          "dep": "punct",
          "governor": 3,
          "governorGloss": "wished",
          "dependent": 8,
          "dependentGloss": ","
        },
        {
          "dep": "mark",
          "governor": 10,
          "governorGloss": "speak",
          "dependent": 9,
          "dependentGloss": "to"
        },
        {
          "dep": "xcomp",
          "governor": 3,
          "governorGloss": "wished",
          "dependent": 10,
          "dependentGloss": "speak"
        },
        {
          "dep": "advmod",
          "governor": 10,
          "governorGloss": "speak",
          "dependent": 11,
          "dependentGloss": "well"
        },
        {
          "dep": "punct",
          "governor": 3,
          "governorGloss": "wished",
          "dependent": 12,
          "dependentGloss": ","
        },
        {
          "dep": "cc",
          "governor": 3,
          "governorGloss": "wished",
          "dependent": 13,
          "dependentGloss": "but"
        },
        {
          "dep": "nsubj",
          "governor": 17,
          "governorGloss": "wish",
          "dependent": 14,
          "dependentGloss": "he"
        },
        {
          "dep": "aux",
          "governor": 17,
          "governorGloss": "wish",
          "dependent": 15,
          "dependentGloss": "would"
        },
        {
          "dep": "neg",
          "governor": 17,
          "governorGloss": "wish",
          "dependent": 16,
          "dependentGloss": "never"
        },
        {
          "dep": "conj:but",
          "governor": 3,
          "governorGloss": "wished",
          "dependent": 17,
          "dependentGloss": "wish"
        },
        {
          "dep": "nmod:poss",
          "governor": 20,
          "governorGloss": "daughters",
          "dependent": 18,
          "dependentGloss": "his"
        },
        {
          "dep": "amod",
          "governor": 20,
          "governorGloss": "daughters",
          "dependent": 19,
          "dependentGloss": "grownup"
        },
        {
          "dep": "dobj",
          "governor": 17,
          "governorGloss": "wish",
          "dependent": 20,
          "dependentGloss": "daughters"
        },
        {
          "dep": "mark",
          "governor": 23,
          "governorGloss": "acting",
          "dependent": 21,
          "dependentGloss": "to"
        },
        {
          "dep": "aux",
          "governor": 23,
          "governorGloss": "acting",
          "dependent": 22,
          "dependentGloss": "be"
        },
        {
          "dep": "xcomp",
          "governor": 17,
          "governorGloss": "wish",
          "dependent": 23,
          "dependentGloss": "acting"
        },
        {
          "dep": "dobj",
          "governor": 23,
          "governorGloss": "acting",
          "dependent": 24,
          "dependentGloss": "plays"
        },
        {
          "dep": "punct",
          "governor": 3,
          "governorGloss": "wished",
          "dependent": 25,
          "dependentGloss": "."
        }
      ],
      "tokens": [
        {
          "index": 1,
          "word": "My",
          "originalText": "My",
          "lemma": "my",
          "characterOffsetBegin": 0,
          "characterOffsetEnd": 2,
          "pos": "PRP$",
          "ner": "O",
          "before": "",
          "after": " "
        },
        {
          "index": 2,
          "word": "father",
          "originalText": "father",
          "lemma": "father",
          "characterOffsetBegin": 3,
          "characterOffsetEnd": 9,
          "pos": "NN",
          "ner": "O",
          "before": " ",
          "after": " "
        },
        {
          "index": 3,
          "word": "wished",
          "originalText": "wished",
          "lemma": "wish",
          "characterOffsetBegin": 10,
          "characterOffsetEnd": 16,
          "pos": "VBD",
          "ner": "O",
          "before": " ",
          "after": " "
        },
        {
          "index": 4,
          "word": "us",
          "originalText": "us",
          "lemma": "we",
          "characterOffsetBegin": 17,
          "characterOffsetEnd": 19,
          "pos": "PRP",
          "ner": "O",
          "before": " ",
          "after": ""
        },
        {
          "index": 5,
          "word": ",",
          "originalText": ",",
          "lemma": ",",
          "characterOffsetBegin": 19,
          "characterOffsetEnd": 20,
          "pos": ",",
          "ner": "O",
          "before": "",
          "after": " "
        },
        {
          "index": 6,
          "word": "as",
          "originalText": "as",
          "lemma": "as",
          "characterOffsetBegin": 21,
          "characterOffsetEnd": 23,
          "pos": "IN",
          "ner": "O",
          "before": " ",
          "after": " "
        },
        {
          "index": 7,
          "word": "schoolboys",
          "originalText": "schoolboys",
          "lemma": "schoolboy",
          "characterOffsetBegin": 24,
          "characterOffsetEnd": 34,
          "pos": "NNS",
          "ner": "O",
          "before": " ",
          "after": ""
        },
        {
          "index": 8,
          "word": ",",
          "originalText": ",",
          "lemma": ",",
          "characterOffsetBegin": 34,
          "characterOffsetEnd": 35,
          "pos": ",",
          "ner": "O",
          "before": "",
          "after": " "
        },
        {
          "index": 9,
          "word": "to",
          "originalText": "to",
          "lemma": "to",
          "characterOffsetBegin": 36,
          "characterOffsetEnd": 38,
          "pos": "TO",
          "ner": "O",
          "before": " ",
          "after": " "
        },
        {
          "index": 10,
          "word": "speak",
          "originalText": "speak",
          "lemma": "speak",
          "characterOffsetBegin": 39,
          "characterOffsetEnd": 44,
          "pos": "VB",
          "ner": "O",
          "before": " ",
          "after": " "
        },
        {
          "index": 11,
          "word": "well",
          "originalText": "well",
          "lemma": "well",
          "characterOffsetBegin": 45,
          "characterOffsetEnd": 49,
          "pos": "RB",
          "ner": "O",
          "before": " ",
          "after": ""
        },
        {
          "index": 12,
          "word": ",",
          "originalText": ",",
          "lemma": ",",
          "characterOffsetBegin": 49,
          "characterOffsetEnd": 50,
          "pos": ",",
          "ner": "O",
          "before": "",
          "after": " "
        },
        {
          "index": 13,
          "word": "but",
          "originalText": "but",
          "lemma": "but",
          "characterOffsetBegin": 51,
          "characterOffsetEnd": 54,
          "pos": "CC",
          "ner": "O",
          "before": " ",
          "after": " "
        },
        {
          "index": 14,
          "word": "he",
          "originalText": "he",
          "lemma": "he",
          "characterOffsetBegin": 55,
          "characterOffsetEnd": 57,
          "pos": "PRP",
          "ner": "O",
          "before": " ",
          "after": " "
        },
        {
          "index": 15,
          "word": "would",
          "originalText": "would",
          "lemma": "would",
          "characterOffsetBegin": 58,
          "characterOffsetEnd": 63,
          "pos": "MD",
          "ner": "O",
          "before": " ",
          "after": " "
        },
        {
          "index": 16,
          "word": "never",
          "originalText": "never",
          "lemma": "never",
          "characterOffsetBegin": 64,
          "characterOffsetEnd": 69,
          "pos": "RB",
          "ner": "O",
          "before": " ",
          "after": " "
        },
        {
          "index": 17,
          "word": "wish",
          "originalText": "wish",
          "lemma": "wish",
          "characterOffsetBegin": 70,
          "characterOffsetEnd": 74,
          "pos": "VB",
          "ner": "O",
          "before": " ",
          "after": " "
        },
        {
          "index": 18,
          "word": "his",
          "originalText": "his",
          "lemma": "he",
          "characterOffsetBegin": 75,
          "characterOffsetEnd": 78,
          "pos": "PRP$",
          "ner": "O",
          "before": " ",
          "after": " "
        },
        {
          "index": 19,
          "word": "grownup",
          "originalText": "grownup",
          "lemma": "grownup",
          "characterOffsetBegin": 79,
          "characterOffsetEnd": 86,
          "pos": "JJ",
          "ner": "O",
          "before": " ",
          "after": " "
        },
        {
          "index": 20,
          "word": "daughters",
          "originalText": "daughters",
          "lemma": "daughter",
          "characterOffsetBegin": 87,
          "characterOffsetEnd": 96,
          "pos": "NNS",
          "ner": "O",
          "before": " ",
          "after": " "
        },
        {
          "index": 21,
          "word": "to",
          "originalText": "to",
          "lemma": "to",
          "characterOffsetBegin": 97,
          "characterOffsetEnd": 99,
          "pos": "TO",
          "ner": "O",
          "before": " ",
          "after": " "
        },
        {
          "index": 22,
          "word": "be",
          "originalText": "be",
          "lemma": "be",
          "characterOffsetBegin": 100,
          "characterOffsetEnd": 102,
          "pos": "VB",
          "ner": "O",
          "before": " ",
          "after": " "
        },
        {
          "index": 23,
          "word": "acting",
          "originalText": "acting",
          "lemma": "act",
          "characterOffsetBegin": 103,
          "characterOffsetEnd": 109,
          "pos": "VBG",
          "ner": "O",
          "before": " ",
          "after": " "
        },
        {
          "index": 24,
          "word": "plays",
          "originalText": "plays",
          "lemma": "play",
          "characterOffsetBegin": 110,
          "characterOffsetEnd": 115,
          "pos": "NNS",
          "ner": "O",
          "before": " ",
          "after": ""
        },
        {
          "index": 25,
          "word": ".",
          "originalText": ".",
          "lemma": ".",
          "characterOffsetBegin": 115,
          "characterOffsetEnd": 116,
          "pos": ".",
          "ner": "O",
          "before": "",
          "after": " "
        }
      ]
    },
    {
      "index": 1,
      "parse": "(ROOT\n  (S\n    (NP\n      (NP (PRP$ His) (NN sense))\n      (PP (IN of)\n        (NP (NN decorum))))\n    (VP (VBZ is)\n      (NP (JJ strict)))\n    (. .)))",
      "basic-dependencies": [
        {
          "dep": "ROOT",
          "governor": 0,
          "governorGloss": "ROOT",
          "dependent": 6,
          "dependentGloss": "strict"
        },
        {
          "dep": "nmod:poss",
          "governor": 2,
          "governorGloss": "sense",
          "dependent": 1,
          "dependentGloss": "His"
        },
        {
          "dep": "nsubj",
          "governor": 6,
          "governorGloss": "strict",
          "dependent": 2,
          "dependentGloss": "sense"
        },
        {
          "dep": "case",
          "governor": 4,
          "governorGloss": "decorum",
          "dependent": 3,
          "dependentGloss": "of"
        },
        {
          "dep": "nmod",
          "governor": 2,
          "governorGloss": "sense",
          "dependent": 4,
          "dependentGloss": "decorum"
        },
        {
          "dep": "cop",
          "governor": 6,
          "governorGloss": "strict",
          "dependent": 5,
          "dependentGloss": "is"
        },
        {
          "dep": "punct",
          "governor": 6,
          "governorGloss": "strict",
          "dependent": 7,
          "dependentGloss": "."
        }
      ],
      "collapsed-dependencies": [
        {
          "dep": "ROOT",
          "governor": 0,
          "governorGloss": "ROOT",
          "dependent": 6,
          "dependentGloss": "strict"
        },
        {
          "dep": "nmod:poss",
          "governor": 2,
          "governorGloss": "sense",
          "dependent": 1,
          "dependentGloss": "His"
        },
        {
          "dep": "nsubj",
          "governor": 6,
          "governorGloss": "strict",
          "dependent": 2,
          "dependentGloss": "sense"
        },
        {
          "dep": "case",
          "governor": 4,
          "governorGloss": "decorum",
          "dependent": 3,
          "dependentGloss": "of"
        },
        {
          "dep": "nmod:of",
          "governor": 2,
          "governorGloss": "sense",
          "dependent": 4,
          "dependentGloss": "decorum"
        },
        {
          "dep": "cop",
          "governor": 6,
          "governorGloss": "strict",
          "dependent": 5,
          "dependentGloss": "is"
        },
        {
          "dep": "punct",
          "governor": 6,
          "governorGloss": "strict",
          "dependent": 7,
          "dependentGloss": "."
        }
      ],
      "collapsed-ccprocessed-dependencies": [
        {
          "dep": "ROOT",
          "governor": 0,
          "governorGloss": "ROOT",
          "dependent": 6,
          "dependentGloss": "strict"
        },
        {
          "dep": "nmod:poss",
          "governor": 2,
          "governorGloss": "sense",
          "dependent": 1,
          "dependentGloss": "His"
        },
        {
          "dep": "nsubj",
          "governor": 6,
          "governorGloss": "strict",
          "dependent": 2,
          "dependentGloss": "sense"
        },
        {
          "dep": "case",
          "governor": 4,
          "governorGloss": "decorum",
          "dependent": 3,
          "dependentGloss": "of"
        },
        {
          "dep": "nmod:of",
          "governor": 2,
          "governorGloss": "sense",
          "dependent": 4,
          "dependentGloss": "decorum"
        },
        {
          "dep": "cop",
          "governor": 6,
          "governorGloss": "strict",
          "dependent": 5,
          "dependentGloss": "is"
        },
        {
          "dep": "punct",
          "governor": 6,
          "governorGloss": "strict",
          "dependent": 7,
          "dependentGloss": "."
        }
      ],
      "tokens": [
        {
          "index": 1,
          "word": "His",
          "originalText": "His",
          "lemma": "he",
          "characterOffsetBegin": 117,
          "characterOffsetEnd": 120,
          "pos": "PRP$",
          "ner": "O",
          "before": " ",
          "after": " "
        },
        {
          "index": 2,
          "word": "sense",
          "originalText": "sense",
          "lemma": "sense",
          "characterOffsetBegin": 121,
          "characterOffsetEnd": 126,
          "pos": "NN",
          "ner": "O",
          "before": " ",
          "after": " "
        },
        {
          "index": 3,
          "word": "of",
          "originalText": "of",
          "lemma": "of",
          "characterOffsetBegin": 127,
          "characterOffsetEnd": 129,
          "pos": "IN",
          "ner": "O",
          "before": " ",
          "after": " "
        },
        {
          "index": 4,
          "word": "decorum",
          "originalText": "decorum",
          "lemma": "decorum",
          "characterOffsetBegin": 130,
          "characterOffsetEnd": 137,
          "pos": "NN",
          "ner": "O",
          "before": " ",
          "after": " "
        },
        {
          "index": 5,
          "word": "is",
          "originalText": "is",
          "lemma": "be",
          "characterOffsetBegin": 138,
          "characterOffsetEnd": 140,
          "pos": "VBZ",
          "ner": "O",
          "before": " ",
          "after": " "
        },
        {
          "index": 6,
          "word": "strict",
          "originalText": "strict",
          "lemma": "strict",
          "characterOffsetBegin": 141,
          "characterOffsetEnd": 147,
          "pos": "JJ",
          "ner": "O",
          "before": " ",
          "after": ""
        },
        {
          "index": 7,
          "word": ".",
          "originalText": ".",
          "lemma": ".",
          "characterOffsetBegin": 147,
          "characterOffsetEnd": 148,
          "pos": ".",
          "ner": "O",
          "before": "",
          "after": " "
        }
      ]
    },
    {
      "index": 2,
      "parse": "(ROOT\n  (S\n    (S\n      (NP (PRP I))\n      (VP (VBP know)\n        (S\n          (NP (DT all))\n          (NP (DT that)))))\n    (, ,)\n    (NP (PRP I))\n    (VP (VBP know)\n      (NP (PRP$ my) (NN father))\n      (ADVP\n        (ADVP (RB as) (RB well))\n        (SBAR (IN as)\n          (S\n            (NP (PRP you))\n            (VP (VBP do))))))\n    (. .)))",
      "basic-dependencies": [
        {
          "dep": "ROOT",
          "governor": 0,
          "governorGloss": "ROOT",
          "dependent": 2,
          "dependentGloss": "know"
        },
        {
          "dep": "nsubj",
          "governor": 2,
          "governorGloss": "know",
          "dependent": 1,
          "dependentGloss": "I"
        },
        {
          "dep": "det",
          "governor": 4,
          "governorGloss": "that",
          "dependent": 3,
          "dependentGloss": "all"
        },
        {
          "dep": "dobj",
          "governor": 2,
          "governorGloss": "know",
          "dependent": 4,
          "dependentGloss": "that"
        },
        {
          "dep": "punct",
          "governor": 7,
          "governorGloss": "know",
          "dependent": 5,
          "dependentGloss": ","
        },
        {
          "dep": "nsubj",
          "governor": 7,
          "governorGloss": "know",
          "dependent": 6,
          "dependentGloss": "I"
        },
        {
          "dep": "acl:relcl",
          "governor": 4,
          "governorGloss": "that",
          "dependent": 7,
          "dependentGloss": "know"
        },
        {
          "dep": "nmod:poss",
          "governor": 9,
          "governorGloss": "father",
          "dependent": 8,
          "dependentGloss": "my"
        },
        {
          "dep": "nsubj",
          "governor": 14,
          "governorGloss": "do",
          "dependent": 9,
          "dependentGloss": "father"
        },
        {
          "dep": "cc",
          "governor": 9,
          "governorGloss": "father",
          "dependent": 10,
          "dependentGloss": "as"
        },
        {
          "dep": "mwe",
          "governor": 10,
          "governorGloss": "as",
          "dependent": 11,
          "dependentGloss": "well"
        },
        {
          "dep": "mwe",
          "governor": 10,
          "governorGloss": "as",
          "dependent": 12,
          "dependentGloss": "as"
        },
        {
          "dep": "conj",
          "governor": 9,
          "governorGloss": "father",
          "dependent": 13,
          "dependentGloss": "you"
        },
        {
          "dep": "ccomp",
          "governor": 7,
          "governorGloss": "know",
          "dependent": 14,
          "dependentGloss": "do"
        },
        {
          "dep": "punct",
          "governor": 2,
          "governorGloss": "know",
          "dependent": 15,
          "dependentGloss": "."
        }
      ],
      "collapsed-dependencies": [
        {
          "dep": "ROOT",
          "governor": 0,
          "governorGloss": "ROOT",
          "dependent": 2,
          "dependentGloss": "know"
        },
        {
          "dep": "nsubj",
          "governor": 2,
          "governorGloss": "know",
          "dependent": 1,
          "dependentGloss": "I"
        },
        {
          "dep": "det",
          "governor": 4,
          "governorGloss": "that",
          "dependent": 3,
          "dependentGloss": "all"
        },
        {
          "dep": "dobj",
          "governor": 2,
          "governorGloss": "know",
          "dependent": 4,
          "dependentGloss": "that"
        },
        {
          "dep": "punct",
          "governor": 7,
          "governorGloss": "know",
          "dependent": 5,
          "dependentGloss": ","
        },
        {
          "dep": "nsubj",
          "governor": 7,
          "governorGloss": "know",
          "dependent": 6,
          "dependentGloss": "I"
        },
        {
          "dep": "acl:relcl",
          "governor": 4,
          "governorGloss": "that",
          "dependent": 7,
          "dependentGloss": "know"
        },
        {
          "dep": "nmod:poss",
          "governor": 9,
          "governorGloss": "father",
          "dependent": 8,
          "dependentGloss": "my"
        },
        {
          "dep": "nsubj",
          "governor": 14,
          "governorGloss": "do",
          "dependent": 9,
          "dependentGloss": "father"
        },
        {
          "dep": "cc",
          "governor": 9,
          "governorGloss": "father",
          "dependent": 10,
          "dependentGloss": "as"
        },
        {
          "dep": "mwe",
          "governor": 10,
          "governorGloss": "as",
          "dependent": 11,
          "dependentGloss": "well"
        },
        {
          "dep": "mwe",
          "governor": 10,
          "governorGloss": "as",
          "dependent": 12,
          "dependentGloss": "as"
        },
        {
          "dep": "conj:and",
          "governor": 9,
          "governorGloss": "father",
          "dependent": 13,
          "dependentGloss": "you"
        },
        {
          "dep": "ccomp",
          "governor": 7,
          "governorGloss": "know",
          "dependent": 14,
          "dependentGloss": "do"
        },
        {
          "dep": "punct",
          "governor": 2,
          "governorGloss": "know",
          "dependent": 15,
          "dependentGloss": "."
        }
      ],
      "collapsed-ccprocessed-dependencies": [
        {
          "dep": "ROOT",
          "governor": 0,
          "governorGloss": "ROOT",
          "dependent": 2,
          "dependentGloss": "know"
        },
        {
          "dep": "nsubj",
          "governor": 2,
          "governorGloss": "know",
          "dependent": 1,
          "dependentGloss": "I"
        },
        {
          "dep": "det",
          "governor": 4,
          "governorGloss": "that",
          "dependent": 3,
          "dependentGloss": "all"
        },
        {
          "dep": "dobj",
          "governor": 2,
          "governorGloss": "know",
          "dependent": 4,
          "dependentGloss": "that"
        },
        {
          "dep": "punct",
          "governor": 7,
          "governorGloss": "know",
          "dependent": 5,
          "dependentGloss": ","
        },
        {
          "dep": "nsubj",
          "governor": 7,
          "governorGloss": "know",
          "dependent": 6,
          "dependentGloss": "I"
        },
        {
          "dep": "acl:relcl",
          "governor": 4,
          "governorGloss": "that",
          "dependent": 7,
          "dependentGloss": "know"
        },
        {
          "dep": "nmod:poss",
          "governor": 9,
          "governorGloss": "father",
          "dependent": 8,
          "dependentGloss": "my"
        },
        {
          "dep": "nsubj",
          "governor": 14,
          "governorGloss": "do",
          "dependent": 9,
          "dependentGloss": "father"
        },
        {
          "dep": "cc",
          "governor": 9,
          "governorGloss": "father",
          "dependent": 10,
          "dependentGloss": "as"
        },
        {
          "dep": "mwe",
          "governor": 10,
          "governorGloss": "as",
          "dependent": 11,
          "dependentGloss": "well"
        },
        {
          "dep": "mwe",
          "governor": 10,
          "governorGloss": "as",
          "dependent": 12,
          "dependentGloss": "as"
        },
        {
          "dep": "conj:and",
          "governor": 9,
          "governorGloss": "father",
          "dependent": 13,
          "dependentGloss": "you"
        },
        {
          "dep": "nsubj",
          "governor": 14,
          "governorGloss": "do",
          "dependent": 13,
          "dependentGloss": "you"
        },
        {
          "dep": "ccomp",
          "governor": 7,
          "governorGloss": "know",
          "dependent": 14,
          "dependentGloss": "do"
        },
        {
          "dep": "punct",
          "governor": 2,
          "governorGloss": "know",
          "dependent": 15,
          "dependentGloss": "."
        }
      ],
      "tokens": [
        {
          "index": 1,
          "word": "I",
          "originalText": "I",
          "lemma": "I",
          "characterOffsetBegin": 149,
          "characterOffsetEnd": 150,
          "pos": "PRP",
          "ner": "O",
          "before": " ",
          "after": " "
        },
        {
          "index": 2,
          "word": "know",
          "originalText": "know",
          "lemma": "know",
          "characterOffsetBegin": 151,
          "characterOffsetEnd": 155,
          "pos": "VBP",
          "ner": "O",
          "before": " ",
          "after": " "
        },
        {
          "index": 3,
          "word": "all",
          "originalText": "all",
          "lemma": "all",
          "characterOffsetBegin": 156,
          "characterOffsetEnd": 159,
          "pos": "DT",
          "ner": "O",
          "before": " ",
          "after": " "
        },
        {
          "index": 4,
          "word": "that",
          "originalText": "that",
          "lemma": "that",
          "characterOffsetBegin": 160,
          "characterOffsetEnd": 164,
          "pos": "DT",
          "ner": "O",
          "before": " ",
          "after": ""
        },
        {
          "index": 5,
          "word": ",",
          "originalText": ",",
          "lemma": ",",
          "characterOffsetBegin": 164,
          "characterOffsetEnd": 165,
          "pos": ",",
          "ner": "O",
          "before": "",
          "after": " "
        },
        {
          "index": 6,
          "word": "I",
          "originalText": "I",
          "lemma": "I",
          "characterOffsetBegin": 166,
          "characterOffsetEnd": 167,
          "pos": "PRP",
          "ner": "O",
          "before": " ",
          "after": " "
        },
        {
          "index": 7,
          "word": "know",
          "originalText": "know",
          "lemma": "know",
          "characterOffsetBegin": 168,
          "characterOffsetEnd": 172,
          "pos": "VBP",
          "ner": "O",
          "before": " ",
          "after": " "
        },
        {
          "index": 8,
          "word": "my",
          "originalText": "my",
          "lemma": "my",
          "characterOffsetBegin": 173,
          "characterOffsetEnd": 175,
          "pos": "PRP$",
          "ner": "O",
          "before": " ",
          "after": " "
        },
        {
          "index": 9,
          "word": "father",
          "originalText": "father",
          "lemma": "father",
          "characterOffsetBegin": 176,
          "characterOffsetEnd": 182,
          "pos": "NN",
          "ner": "O",
          "before": " ",
          "after": " "
        },
        {
          "index": 10,
          "word": "as",
          "originalText": "as",
          "lemma": "as",
          "characterOffsetBegin": 183,
          "characterOffsetEnd": 185,
          "pos": "RB",
          "ner": "O",
          "before": " ",
          "after": " "
        },
        {
          "index": 11,
          "word": "well",
          "originalText": "well",
          "lemma": "well",
          "characterOffsetBegin": 186,
          "characterOffsetEnd": 190,
          "pos": "RB",
          "ner": "O",
          "before": " ",
          "after": " "
        },
        {
          "index": 12,
          "word": "as",
          "originalText": "as",
          "lemma": "as",
          "characterOffsetBegin": 191,
          "characterOffsetEnd": 193,
          "pos": "IN",
          "ner": "O",
          "before": " ",
          "after": " "
        },
        {
          "index": 13,
          "word": "you",
          "originalText": "you",
          "lemma": "you",
          "characterOffsetBegin": 194,
          "characterOffsetEnd": 197,
          "pos": "PRP",
          "ner": "O",
          "before": " ",
          "after": " "
        },
        {
          "index": 14,
          "word": "do",
          "originalText": "do",
          "lemma": "do",
          "characterOffsetBegin": 198,
          "characterOffsetEnd": 200,
          "pos": "VBP",
          "ner": "O",
          "before": " ",
          "after": ""
        },
        {
          "index": 15,
          "word": ".",
          "originalText": ".",
          "lemma": ".",
          "characterOffsetBegin": 200,
          "characterOffsetEnd": 201,
          "pos": ".",
          "ner": "O",
          "before": "",
          "after": " "
        }
      ]
    },
    {
      "index": 3,
      "parse": "(ROOT\n  (S (CC and)\n    (NP (PRP I))\n    (VP (MD 'll)\n      (VP (VB take)\n        (NP (NN care))\n        (SBAR (IN that)\n          (S\n            (NP (PRP$ his) (NNS daughters))\n            (VP (VBP do)\n              (S\n                (NP\n                  (NP (NN nothing))\n                  (PP (TO to)\n                    (NP (NN distress))))\n                (NP (PRP him))))))))\n    (. .)))",
      "basic-dependencies": [
        {
          "dep": "ROOT",
          "governor": 0,
          "governorGloss": "ROOT",
          "dependent": 4,
          "dependentGloss": "take"
        },
        {
          "dep": "cc",
          "governor": 4,
          "governorGloss": "take",
          "dependent": 1,
          "dependentGloss": "and"
        },
        {
          "dep": "nsubj",
          "governor": 4,
          "governorGloss": "take",
          "dependent": 2,
          "dependentGloss": "I"
        },
        {
          "dep": "aux",
          "governor": 4,
          "governorGloss": "take",
          "dependent": 3,
          "dependentGloss": "'ll"
        },
        {
          "dep": "dobj",
          "governor": 4,
          "governorGloss": "take",
          "dependent": 5,
          "dependentGloss": "care"
        },
        {
          "dep": "mark",
          "governor": 9,
          "governorGloss": "do",
          "dependent": 6,
          "dependentGloss": "that"
        },
        {
          "dep": "nmod:poss",
          "governor": 8,
          "governorGloss": "daughters",
          "dependent": 7,
          "dependentGloss": "his"
        },
        {
          "dep": "nsubj",
          "governor": 9,
          "governorGloss": "do",
          "dependent": 8,
          "dependentGloss": "daughters"
        },
        {
          "dep": "ccomp",
          "governor": 5,
          "governorGloss": "care",
          "dependent": 9,
          "dependentGloss": "do"
        },
        {
          "dep": "dobj",
          "governor": 9,
          "governorGloss": "do",
          "dependent": 10,
          "dependentGloss": "nothing"
        },
        {
          "dep": "case",
          "governor": 12,
          "governorGloss": "distress",
          "dependent": 11,
          "dependentGloss": "to"
        },
        {
          "dep": "nmod",
          "governor": 10,
          "governorGloss": "nothing",
          "dependent": 12,
          "dependentGloss": "distress"
        },
        {
          "dep": "dep",
          "governor": 12,
          "governorGloss": "distress",
          "dependent": 13,
          "dependentGloss": "him"
        },
        {
          "dep": "punct",
          "governor": 4,
          "governorGloss": "take",
          "dependent": 14,
          "dependentGloss": "."
        }
      ],
      "collapsed-dependencies": [
        {
          "dep": "ROOT",
          "governor": 0,
          "governorGloss": "ROOT",
          "dependent": 4,
          "dependentGloss": "take"
        },
        {
          "dep": "cc",
          "governor": 4,
          "governorGloss": "take",
          "dependent": 1,
          "dependentGloss": "and"
        },
        {
          "dep": "nsubj",
          "governor": 4,
          "governorGloss": "take",
          "dependent": 2,
          "dependentGloss": "I"
        },
        {
          "dep": "aux",
          "governor": 4,
          "governorGloss": "take",
          "dependent": 3,
          "dependentGloss": "'ll"
        },
        {
          "dep": "dobj",
          "governor": 4,
          "governorGloss": "take",
          "dependent": 5,
          "dependentGloss": "care"
        },
        {
          "dep": "mark",
          "governor": 9,
          "governorGloss": "do",
          "dependent": 6,
          "dependentGloss": "that"
        },
        {
          "dep": "nmod:poss",
          "governor": 8,
          "governorGloss": "daughters",
          "dependent": 7,
          "dependentGloss": "his"
        },
        {
          "dep": "nsubj",
          "governor": 9,
          "governorGloss": "do",
          "dependent": 8,
          "dependentGloss": "daughters"
        },
        {
          "dep": "ccomp",
          "governor": 5,
          "governorGloss": "care",
          "dependent": 9,
          "dependentGloss": "do"
        },
        {
          "dep": "dobj",
          "governor": 9,
          "governorGloss": "do",
          "dependent": 10,
          "dependentGloss": "nothing"
        },
        {
          "dep": "case",
          "governor": 12,
          "governorGloss": "distress",
          "dependent": 11,
          "dependentGloss": "to"
        },
        {
          "dep": "nmod:to",
          "governor": 10,
          "governorGloss": "nothing",
          "dependent": 12,
          "dependentGloss": "distress"
        },
        {
          "dep": "dep",
          "governor": 12,
          "governorGloss": "distress",
          "dependent": 13,
          "dependentGloss": "him"
        },
        {
          "dep": "punct",
          "governor": 4,
          "governorGloss": "take",
          "dependent": 14,
          "dependentGloss": "."
        }
      ],
      "collapsed-ccprocessed-dependencies": [
        {
          "dep": "ROOT",
          "governor": 0,
          "governorGloss": "ROOT",
          "dependent": 4,
          "dependentGloss": "take"
        },
        {
          "dep": "cc",
          "governor": 4,
          "governorGloss": "take",
          "dependent": 1,
          "dependentGloss": "and"
        },
        {
          "dep": "nsubj",
          "governor": 4,
          "governorGloss": "take",
          "dependent": 2,
          "dependentGloss": "I"
        },
        {
          "dep": "aux",
          "governor": 4,
          "governorGloss": "take",
          "dependent": 3,
          "dependentGloss": "'ll"
        },
        {
          "dep": "dobj",
          "governor": 4,
          "governorGloss": "take",
          "dependent": 5,
          "dependentGloss": "care"
        },
        {
          "dep": "mark",
          "governor": 9,
          "governorGloss": "do",
          "dependent": 6,
          "dependentGloss": "that"
        },
        {
          "dep": "nmod:poss",
          "governor": 8,
          "governorGloss": "daughters",
          "dependent": 7,
          "dependentGloss": "his"
        },
        {
          "dep": "nsubj",
          "governor": 9,
          "governorGloss": "do",
          "dependent": 8,
          "dependentGloss": "daughters"
        },
        {
          "dep": "ccomp",
          "governor": 5,
          "governorGloss": "care",
          "dependent": 9,
          "dependentGloss": "do"
        },
        {
          "dep": "dobj",
          "governor": 9,
          "governorGloss": "do",
          "dependent": 10,
          "dependentGloss": "nothing"
        },
        {
          "dep": "case",
          "governor": 12,
          "governorGloss": "distress",
          "dependent": 11,
          "dependentGloss": "to"
        },
        {
          "dep": "nmod:to",
          "governor": 10,
          "governorGloss": "nothing",
          "dependent": 12,
          "dependentGloss": "distress"
        },
        {
          "dep": "dep",
          "governor": 12,
          "governorGloss": "distress",
          "dependent": 13,
          "dependentGloss": "him"
        },
        {
          "dep": "punct",
          "governor": 4,
          "governorGloss": "take",
          "dependent": 14,
          "dependentGloss": "."
        }
      ],
      "tokens": [
        {
          "index": 1,
          "word": "and",
          "originalText": "and",
          "lemma": "and",
          "characterOffsetBegin": 202,
          "characterOffsetEnd": 205,
          "pos": "CC",
          "ner": "O",
          "before": " ",
          "after": " "
        },
        {
          "index": 2,
          "word": "I",
          "originalText": "I",
          "lemma": "I",
          "characterOffsetBegin": 206,
          "characterOffsetEnd": 207,
          "pos": "PRP",
          "ner": "O",
          "before": " ",
          "after": ""
        },
        {
          "index": 3,
          "word": "'ll",
          "originalText": "'ll",
          "lemma": "will",
          "characterOffsetBegin": 207,
          "characterOffsetEnd": 210,
          "pos": "MD",
          "ner": "O",
          "before": "",
          "after": " "
        },
        {
          "index": 4,
          "word": "take",
          "originalText": "take",
          "lemma": "take",
          "characterOffsetBegin": 211,
          "characterOffsetEnd": 215,
          "pos": "VB",
          "ner": "O",
          "before": " ",
          "after": " "
        },
        {
          "index": 5,
          "word": "care",
          "originalText": "care",
          "lemma": "care",
          "characterOffsetBegin": 216,
          "characterOffsetEnd": 220,
          "pos": "NN",
          "ner": "O",
          "before": " ",
          "after": " "
        },
        {
          "index": 6,
          "word": "that",
          "originalText": "that",
          "lemma": "that",
          "characterOffsetBegin": 221,
          "characterOffsetEnd": 225,
          "pos": "IN",
          "ner": "O",
          "before": " ",
          "after": " "
        },
        {
          "index": 7,
          "word": "his",
          "originalText": "his",
          "lemma": "he",
          "characterOffsetBegin": 226,
          "characterOffsetEnd": 229,
          "pos": "PRP$",
          "ner": "O",
          "before": " ",
          "after": " "
        },
        {
          "index": 8,
          "word": "daughters",
          "originalText": "daughters",
          "lemma": "daughter",
          "characterOffsetBegin": 230,
          "characterOffsetEnd": 239,
          "pos": "NNS",
          "ner": "O",
          "before": " ",
          "after": " "
        },
        {
          "index": 9,
          "word": "do",
          "originalText": "do",
          "lemma": "do",
          "characterOffsetBegin": 240,
          "characterOffsetEnd": 242,
          "pos": "VBP",
          "ner": "O",
          "before": " ",
          "after": " "
        },
        {
          "index": 10,
          "word": "nothing",
          "originalText": "nothing",
          "lemma": "nothing",
          "characterOffsetBegin": 243,
          "characterOffsetEnd": 250,
          "pos": "NN",
          "ner": "O",
          "before": " ",
          "after": " "
        },
        {
          "index": 11,
          "word": "to",
          "originalText": "to",
          "lemma": "to",
          "characterOffsetBegin": 251,
          "characterOffsetEnd": 253,
          "pos": "TO",
          "ner": "O",
          "before": " ",
          "after": " "
        },
        {
          "index": 12,
          "word": "distress",
          "originalText": "distress",
          "lemma": "distress",
          "characterOffsetBegin": 254,
          "characterOffsetEnd": 262,
          "pos": "NN",
          "ner": "O",
          "before": " ",
          "after": " "
        },
        {
          "index": 13,
          "word": "him",
          "originalText": "him",
          "lemma": "he",
          "characterOffsetBegin": 263,
          "characterOffsetEnd": 266,
          "pos": "PRP",
          "ner": "O",
          "before": " ",
          "after": ""
        },
        {
          "index": 14,
          "word": ".",
          "originalText": ".",
          "lemma": ".",
          "characterOffsetBegin": 266,
          "characterOffsetEnd": 267,
          "pos": ".",
          "ner": "O",
          "before": "",
          "after": " "
        }
      ]
    },
    {
      "index": 4,
      "parse": "(ROOT\n  (S\n    (S\n      (VP (VB Manage)\n        (NP\n          (NP (PRP$ your) (JJ own) (NNS concerns))\n          (, ,)\n          (NP (NNP Edmund)))))\n    (, ,)\n    (CC and)\n    (S\n      (NP (PRP I))\n      (VP (MD 'll)\n        (VP (VB take)\n          (NP\n            (NP (NN care))\n            (PP (IN of)\n              (NP\n                (NP (DT the) (NN rest))\n                (PP (IN of)\n                  (NP (DT the) (NN family)))))))))\n    (. .)))",
      "basic-dependencies": [
        {
          "dep": "ROOT",
          "governor": 0,
          "governorGloss": "ROOT",
          "dependent": 1,
          "dependentGloss": "Manage"
        },
        {
          "dep": "nmod:poss",
          "governor": 4,
          "governorGloss": "concerns",
          "dependent": 2,
          "dependentGloss": "your"
        },
        {
          "dep": "amod",
          "governor": 4,
          "governorGloss": "concerns",
          "dependent": 3,
          "dependentGloss": "own"
        },
        {
          "dep": "dobj",
          "governor": 1,
          "governorGloss": "Manage",
          "dependent": 4,
          "dependentGloss": "concerns"
        },
        {
          "dep": "punct",
          "governor": 1,
          "governorGloss": "Manage",
          "dependent": 5,
          "dependentGloss": ","
        },
        {
          "dep": "conj",
          "governor": 1,
          "governorGloss": "Manage",
          "dependent": 6,
          "dependentGloss": "Edmund"
        },
        {
          "dep": "punct",
          "governor": 1,
          "governorGloss": "Manage",
          "dependent": 7,
          "dependentGloss": ","
        },
        {
          "dep": "cc",
          "governor": 1,
          "governorGloss": "Manage",
          "dependent": 8,
          "dependentGloss": "and"
        },
        {
          "dep": "nsubj",
          "governor": 11,
          "governorGloss": "take",
          "dependent": 9,
          "dependentGloss": "I"
        },
        {
          "dep": "aux",
          "governor": 11,
          "governorGloss": "take",
          "dependent": 10,
          "dependentGloss": "'ll"
        },
        {
          "dep": "conj",
          "governor": 1,
          "governorGloss": "Manage",
          "dependent": 11,
          "dependentGloss": "take"
        },
        {
          "dep": "dobj",
          "governor": 11,
          "governorGloss": "take",
          "dependent": 12,
          "dependentGloss": "care"
        },
        {
          "dep": "case",
          "governor": 15,
          "governorGloss": "rest",
          "dependent": 13,
          "dependentGloss": "of"
        },
        {
          "dep": "det",
          "governor": 15,
          "governorGloss": "rest",
          "dependent": 14,
          "dependentGloss": "the"
        },
        {
          "dep": "nmod",
          "governor": 12,
          "governorGloss": "care",
          "dependent": 15,
          "dependentGloss": "rest"
        },
        {
          "dep": "case",
          "governor": 18,
          "governorGloss": "family",
          "dependent": 16,
          "dependentGloss": "of"
        },
        {
          "dep": "det",
          "governor": 18,
          "governorGloss": "family",
          "dependent": 17,
          "dependentGloss": "the"
        },
        {
          "dep": "nmod",
          "governor": 15,
          "governorGloss": "rest",
          "dependent": 18,
          "dependentGloss": "family"
        },
        {
          "dep": "punct",
          "governor": 1,
          "governorGloss": "Manage",
          "dependent": 19,
          "dependentGloss": "."
        }
      ],
      "collapsed-dependencies": [
        {
          "dep": "ROOT",
          "governor": 0,
          "governorGloss": "ROOT",
          "dependent": 1,
          "dependentGloss": "Manage"
        },
        {
          "dep": "nmod:poss",
          "governor": 4,
          "governorGloss": "concerns",
          "dependent": 2,
          "dependentGloss": "your"
        },
        {
          "dep": "amod",
          "governor": 4,
          "governorGloss": "concerns",
          "dependent": 3,
          "dependentGloss": "own"
        },
        {
          "dep": "dobj",
          "governor": 1,
          "governorGloss": "Manage",
          "dependent": 4,
          "dependentGloss": "concerns"
        },
        {
          "dep": "punct",
          "governor": 1,
          "governorGloss": "Manage",
          "dependent": 5,
          "dependentGloss": ","
        },
        {
          "dep": "conj:and",
          "governor": 1,
          "governorGloss": "Manage",
          "dependent": 6,
          "dependentGloss": "Edmund"
        },
        {
          "dep": "punct",
          "governor": 1,
          "governorGloss": "Manage",
          "dependent": 7,
          "dependentGloss": ","
        },
        {
          "dep": "cc",
          "governor": 1,
          "governorGloss": "Manage",
          "dependent": 8,
          "dependentGloss": "and"
        },
        {
          "dep": "nsubj",
          "governor": 11,
          "governorGloss": "take",
          "dependent": 9,
          "dependentGloss": "I"
        },
        {
          "dep": "aux",
          "governor": 11,
          "governorGloss": "take",
          "dependent": 10,
          "dependentGloss": "'ll"
        },
        {
          "dep": "conj:and",
          "governor": 1,
          "governorGloss": "Manage",
          "dependent": 11,
          "dependentGloss": "take"
        },
        {
          "dep": "dobj",
          "governor": 11,
          "governorGloss": "take",
          "dependent": 12,
          "dependentGloss": "care"
        },
        {
          "dep": "case",
          "governor": 15,
          "governorGloss": "rest",
          "dependent": 13,
          "dependentGloss": "of"
        },
        {
          "dep": "det",
          "governor": 15,
          "governorGloss": "rest",
          "dependent": 14,
          "dependentGloss": "the"
        },
        {
          "dep": "nmod:of",
          "governor": 12,
          "governorGloss": "care",
          "dependent": 15,
          "dependentGloss": "rest"
        },
        {
          "dep": "case",
          "governor": 18,
          "governorGloss": "family",
          "dependent": 16,
          "dependentGloss": "of"
        },
        {
          "dep": "det",
          "governor": 18,
          "governorGloss": "family",
          "dependent": 17,
          "dependentGloss": "the"
        },
        {
          "dep": "nmod:of",
          "governor": 15,
          "governorGloss": "rest",
          "dependent": 18,
          "dependentGloss": "family"
        },
        {
          "dep": "punct",
          "governor": 1,
          "governorGloss": "Manage",
          "dependent": 19,
          "dependentGloss": "."
        }
      ],
      "collapsed-ccprocessed-dependencies": [
        {
          "dep": "ROOT",
          "governor": 0,
          "governorGloss": "ROOT",
          "dependent": 1,
          "dependentGloss": "Manage"
        },
        {
          "dep": "nmod:poss",
          "governor": 4,
          "governorGloss": "concerns",
          "dependent": 2,
          "dependentGloss": "your"
        },
        {
          "dep": "amod",
          "governor": 4,
          "governorGloss": "concerns",
          "dependent": 3,
          "dependentGloss": "own"
        },
        {
          "dep": "dobj",
          "governor": 1,
          "governorGloss": "Manage",
          "dependent": 4,
          "dependentGloss": "concerns"
        },
        {
          "dep": "punct",
          "governor": 1,
          "governorGloss": "Manage",
          "dependent": 5,
          "dependentGloss": ","
        },
        {
          "dep": "conj:and",
          "governor": 1,
          "governorGloss": "Manage",
          "dependent": 6,
          "dependentGloss": "Edmund"
        },
        {
          "dep": "punct",
          "governor": 1,
          "governorGloss": "Manage",
          "dependent": 7,
          "dependentGloss": ","
        },
        {
          "dep": "cc",
          "governor": 1,
          "governorGloss": "Manage",
          "dependent": 8,
          "dependentGloss": "and"
        },
        {
          "dep": "nsubj",
          "governor": 11,
          "governorGloss": "take",
          "dependent": 9,
          "dependentGloss": "I"
        },
        {
          "dep": "aux",
          "governor": 11,
          "governorGloss": "take",
          "dependent": 10,
          "dependentGloss": "'ll"
        },
        {
          "dep": "conj:and",
          "governor": 1,
          "governorGloss": "Manage",
          "dependent": 11,
          "dependentGloss": "take"
        },
        {
          "dep": "dobj",
          "governor": 11,
          "governorGloss": "take",
          "dependent": 12,
          "dependentGloss": "care"
        },
        {
          "dep": "case",
          "governor": 15,
          "governorGloss": "rest",
          "dependent": 13,
          "dependentGloss": "of"
        },
        {
          "dep": "det",
          "governor": 15,
          "governorGloss": "rest",
          "dependent": 14,
          "dependentGloss": "the"
        },
        {
          "dep": "nmod:of",
          "governor": 12,
          "governorGloss": "care",
          "dependent": 15,
          "dependentGloss": "rest"
        },
        {
          "dep": "case",
          "governor": 18,
          "governorGloss": "family",
          "dependent": 16,
          "dependentGloss": "of"
        },
        {
          "dep": "det",
          "governor": 18,
          "governorGloss": "family",
          "dependent": 17,
          "dependentGloss": "the"
        },
        {
          "dep": "nmod:of",
          "governor": 15,
          "governorGloss": "rest",
          "dependent": 18,
          "dependentGloss": "family"
        },
        {
          "dep": "punct",
          "governor": 1,
          "governorGloss": "Manage",
          "dependent": 19,
          "dependentGloss": "."
        }
      ],
      "tokens": [
        {
          "index": 1,
          "word": "Manage",
          "originalText": "Manage",
          "lemma": "manage",
          "characterOffsetBegin": 268,
          "characterOffsetEnd": 274,
          "pos": "VB",
          "ner": "O",
          "before": " ",
          "after": " "
        },
        {
          "index": 2,
          "word": "your",
          "originalText": "your",
          "lemma": "you",
          "characterOffsetBegin": 275,
          "characterOffsetEnd": 279,
          "pos": "PRP$",
          "ner": "O",
          "before": " ",
          "after": " "
        },
        {
          "index": 3,
          "word": "own",
          "originalText": "own",
          "lemma": "own",
          "characterOffsetBegin": 280,
          "characterOffsetEnd": 283,
          "pos": "JJ",
          "ner": "O",
          "before": " ",
          "after": " "
        },
        {
          "index": 4,
          "word": "concerns",
          "originalText": "concerns",
          "lemma": "concern",
          "characterOffsetBegin": 284,
          "characterOffsetEnd": 292,
          "pos": "NNS",
          "ner": "O",
          "before": " ",
          "after": ""
        },
        {
          "index": 5,
          "word": ",",
          "originalText": ",",
          "lemma": ",",
          "characterOffsetBegin": 292,
          "characterOffsetEnd": 293,
          "pos": ",",
          "ner": "O",
          "before": "",
          "after": " "
        },
        {
          "index": 6,
          "word": "Edmund",
          "originalText": "Edmund",
          "lemma": "Edmund",
          "characterOffsetBegin": 294,
          "characterOffsetEnd": 300,
          "pos": "NNP",
          "ner": "PERSON",
          "before": " ",
          "after": ""
        },
        {
          "index": 7,
          "word": ",",
          "originalText": ",",
          "lemma": ",",
          "characterOffsetBegin": 300,
          "characterOffsetEnd": 301,
          "pos": ",",
          "ner": "O",
          "before": "",
          "after": " "
        },
        {
          "index": 8,
          "word": "and",
          "originalText": "and",
          "lemma": "and",
          "characterOffsetBegin": 302,
          "characterOffsetEnd": 305,
          "pos": "CC",
          "ner": "O",
          "before": " ",
          "after": " "
        },
        {
          "index": 9,
          "word": "I",
          "originalText": "I",
          "lemma": "I",
          "characterOffsetBegin": 306,
          "characterOffsetEnd": 307,
          "pos": "PRP",
          "ner": "O",
          "before": " ",
          "after": ""
        },
        {
          "index": 10,
          "word": "'ll",
          "originalText": "'ll",
          "lemma": "will",
          "characterOffsetBegin": 307,
          "characterOffsetEnd": 310,
          "pos": "MD",
          "ner": "O",
          "before": "",
          "after": " "
        },
        {
          "index": 11,
          "word": "take",
          "originalText": "take",
          "lemma": "take",
          "characterOffsetBegin": 311,
          "characterOffsetEnd": 315,
          "pos": "VB",
          "ner": "O",
          "before": " ",
          "after": " "
        },
        {
          "index": 12,
          "word": "care",
          "originalText": "care",
          "lemma": "care",
          "characterOffsetBegin": 316,
          "characterOffsetEnd": 320,
          "pos": "NN",
          "ner": "O",
          "before": " ",
          "after": " "
        },
        {
          "index": 13,
          "word": "of",
          "originalText": "of",
          "lemma": "of",
          "characterOffsetBegin": 321,
          "characterOffsetEnd": 323,
          "pos": "IN",
          "ner": "O",
          "before": " ",
          "after": " "
        },
        {
          "index": 14,
          "word": "the",
          "originalText": "the",
          "lemma": "the",
          "characterOffsetBegin": 324,
          "characterOffsetEnd": 327,
          "pos": "DT",
          "ner": "O",
          "before": " ",
          "after": " "
        },
        {
          "index": 15,
          "word": "rest",
          "originalText": "rest",
          "lemma": "rest",
          "characterOffsetBegin": 328,
          "characterOffsetEnd": 332,
          "pos": "NN",
          "ner": "O",
          "before": " ",
          "after": " "
        },
        {
          "index": 16,
          "word": "of",
          "originalText": "of",
          "lemma": "of",
          "characterOffsetBegin": 333,
          "characterOffsetEnd": 335,
          "pos": "IN",
          "ner": "O",
          "before": " ",
          "after": " "
        },
        {
          "index": 17,
          "word": "the",
          "originalText": "the",
          "lemma": "the",
          "characterOffsetBegin": 336,
          "characterOffsetEnd": 339,
          "pos": "DT",
          "ner": "O",
          "before": " ",
          "after": " "
        },
        {
          "index": 18,
          "word": "family",
          "originalText": "family",
          "lemma": "family",
          "characterOffsetBegin": 340,
          "characterOffsetEnd": 346,
          "pos": "NN",
          "ner": "O",
          "before": " ",
          "after": ""
        },
        {
          "index": 19,
          "word": ".",
          "originalText": ".",
          "lemma": ".",
          "characterOffsetBegin": 346,
          "characterOffsetEnd": 347,
          "pos": ".",
          "ner": "O",
          "before": "",
          "after": ""
        }
      ]
    }
  ]
}